ZetcodeJavascriptJiaochengChuyiFix1/README.md
ZetcodeJavascriptJiaochengChuyiFix1/__init__.py
ZetcodeJavascriptJiaochengChuyiFix1/__main__.py
ZetcodeJavascriptJiaochengChuyiFix1/file.epub
ZetcodeJavascriptJiaochengChuyiFix1/index.html
ZetcodeJavascriptJiaochengChuyiFix1/css/__init__.py
ZetcodeJavascriptJiaochengChuyiFix1/css/annotations.css
ZetcodeJavascriptJiaochengChuyiFix1/css/main.css
ZetcodeJavascriptJiaochengChuyiFix1/css/normalize.css
ZetcodeJavascriptJiaochengChuyiFix1/css/popup.css
ZetcodeJavascriptJiaochengChuyiFix1/font/__init__.py
ZetcodeJavascriptJiaochengChuyiFix1/font/fontello.eot
ZetcodeJavascriptJiaochengChuyiFix1/font/fontello.svg
ZetcodeJavascriptJiaochengChuyiFix1/font/fontello.ttf
ZetcodeJavascriptJiaochengChuyiFix1/font/fontello.woff
ZetcodeJavascriptJiaochengChuyiFix1/img/__init__.py
ZetcodeJavascriptJiaochengChuyiFix1/img/annotator-glyph-sprite.png
ZetcodeJavascriptJiaochengChuyiFix1/img/annotator-icon-sprite.png
ZetcodeJavascriptJiaochengChuyiFix1/img/apple-touch-icon.png
ZetcodeJavascriptJiaochengChuyiFix1/img/cancelfullscreen.png
ZetcodeJavascriptJiaochengChuyiFix1/img/close.png
ZetcodeJavascriptJiaochengChuyiFix1/img/fullscreen.png
ZetcodeJavascriptJiaochengChuyiFix1/img/loader.gif
ZetcodeJavascriptJiaochengChuyiFix1/img/menu-icon.png
ZetcodeJavascriptJiaochengChuyiFix1/img/save.png
ZetcodeJavascriptJiaochengChuyiFix1/img/saved.png
ZetcodeJavascriptJiaochengChuyiFix1/img/settings-s.png
ZetcodeJavascriptJiaochengChuyiFix1/img/settings.png
ZetcodeJavascriptJiaochengChuyiFix1/img/star.png
ZetcodeJavascriptJiaochengChuyiFix1/js/__init__.py
ZetcodeJavascriptJiaochengChuyiFix1/js/epub.js
ZetcodeJavascriptJiaochengChuyiFix1/js/epub.min.js
ZetcodeJavascriptJiaochengChuyiFix1/js/epub.min.map
ZetcodeJavascriptJiaochengChuyiFix1/js/hooks.min.js
ZetcodeJavascriptJiaochengChuyiFix1/js/hooks.min.map
ZetcodeJavascriptJiaochengChuyiFix1/js/reader.js
ZetcodeJavascriptJiaochengChuyiFix1/js/reader.js.map
ZetcodeJavascriptJiaochengChuyiFix1/js/reader.min.js
zetcode_javascript_jiaocheng_chuyi_fix1-2025.3.24.1.dist-info/METADATA
zetcode_javascript_jiaocheng_chuyi_fix1-2025.3.24.1.dist-info/WHEEL
zetcode_javascript_jiaocheng_chuyi_fix1-2025.3.24.1.dist-info/entry_points.txt
zetcode_javascript_jiaocheng_chuyi_fix1-2025.3.24.1.dist-info/top_level.txt
zetcode_javascript_jiaocheng_chuyi_fix1-2025.3.24.1.dist-info/RECORD
